interzoid_full_name_match_key/__init__.py
interzoid_full_name_match_key/full_name_match_key.py
interzoid_full_name_match_key-1.0.0.dist-info/METADATA
interzoid_full_name_match_key-1.0.0.dist-info/WHEEL
interzoid_full_name_match_key-1.0.0.dist-info/licenses/LICENSE
interzoid_full_name_match_key-1.0.0.dist-info/RECORD
