Metadata-Version: 2.1
Name: interzoid_full_name_match_key
Version: 1.0.0
Summary: Provides an AI-based person name similarity key used to match inconsistent name data.
Project-URL: Homepage, https://www.interzoid.com/apis/individual-name-matching
Author-email: Interzoid <support@interzoid.com>
License-File: LICENSE
Classifier: License :: OSI Approved :: MIT License
Classifier: Operating System :: OS Independent
Classifier: Programming Language :: Python :: 3
Classifier: Topic :: Database
Classifier: Topic :: Scientific/Engineering :: Artificial Intelligence
Classifier: Topic :: Software Development :: Quality Assurance
Requires-Python: >=3.7
